colab_host/__init__.py
colab_host/colab_host.py
colab_host-0.1.9.dist-info/AUTHORS.rst
colab_host-0.1.9.dist-info/LICENSE
colab_host-0.1.9.dist-info/METADATA
colab_host-0.1.9.dist-info/WHEEL
colab_host-0.1.9.dist-info/entry_points.txt
colab_host-0.1.9.dist-info/top_level.txt
colab_host-0.1.9.dist-info/RECORD
