Metadata-Version: 2.1
Name: colab-host
Version: 0.1.9
Summary: Host any python application in colab environment..
Home-page: https://github.com/PuneethaPai/colab_host
Author: Puneetha Pai
Author-email: puneethapai29@gmail.com
License: MIT license
Keywords: colab_host
Platform: UNKNOWN
Classifier: Development Status :: 2 - Pre-Alpha
Classifier: Intended Audience :: Developers
Classifier: License :: OSI Approved :: MIT License
Classifier: Natural Language :: English
Classifier: Programming Language :: Python :: 3
Classifier: Programming Language :: Python :: 3.6
Classifier: Programming Language :: Python :: 3.7
Classifier: Programming Language :: Python :: 3.8
Requires-Python: >=3.6
Requires-Dist: pyngrok (>=4)
Requires-Dist: GitPython (>=3)
